COPYING
MANIFEST.in
README
m4_treap.m4
nest.py
py_treap.py
pyx_treap.c
setup.cfg
setup.py
treap.py
treap_python.egg-info/PKG-INFO
treap_python.egg-info/SOURCES.txt
treap_python.egg-info/dependency_links.txt
treap_python.egg-info/top_level.txt