Metadata-Version: 1.1
Name: treap-python
Version: 1.39
Summary: Python implementation of treaps
Home-page: http://stromberg.dnsalias.org/~dstromberg/treap/
Author: Daniel Richard Stromberg
Author-email: strombrg@gmail.com
License: Apache v2
Platform: Cross platform
Classifier: Development Status :: 5 - Production/Stable
Classifier: Intended Audience :: Developers
Classifier: Programming Language :: Cython
Classifier: Programming Language :: Python :: 2
Classifier: Programming Language :: Python :: 3
